rr/__init__.py
rr/pretty/LICENSE
rr/pretty/VERSION
rr/pretty/__init__.py
rr.pretty-0.1.0.dist-info/DESCRIPTION.rst
rr.pretty-0.1.0.dist-info/METADATA
rr.pretty-0.1.0.dist-info/RECORD
rr.pretty-0.1.0.dist-info/WHEEL
rr.pretty-0.1.0.dist-info/metadata.json
rr.pretty-0.1.0.dist-info/top_level.txt
