Metadata-Version: 2.0
Name: rr.pretty
Version: 0.1.0
Summary: Helpers for creation of nicer repr() and str().
Home-page: https://github.com/2xR/rr.pretty
Author: Rui Jorge Rei
Author-email: rui.jorge.rei@googlemail.com
License: MIT
Platform: UNKNOWN
Classifier: Development Status :: 3 - Alpha
Classifier: License :: OSI Approved :: MIT License
Classifier: Programming Language :: Python :: 2
Classifier: Programming Language :: Python :: 2.7
